aiotracemoeapi/__init__.py
aiotracemoeapi/api_wrapper.py
aiotracemoeapi/exceptions.py
aiotracemoeapi/types.py
aiotracemoeapi/utils.py
aiotracemoeapi-3.1.2.dist-info/WHEEL
aiotracemoeapi-3.1.2.dist-info/METADATA
aiotracemoeapi-3.1.2.dist-info/RECORD
