Metadata-Version: 2.3
Name: aiotracemoeapi
Version: 3.1.2
Summary: Async wrapper for Trace.moe API
Requires-Dist: httpx
Requires-Dist: pydantic>=2.0
Requires-Python: >=3.9
